AUTHORS.rst
CONTRIBUTING.rst
HISTORY.rst
LICENSE
README.md
torchfl/__init__.py
torchfl/cli.py
torchfl/compatibility.py
torchfl/datamodules/__init__.py
torchfl/datamodules/cifar.py
torchfl/datamodules/emnist.py
torchfl/datamodules/fashionmnist.py
torchfl/federated/__init__.py
torchfl/federated/agents/__init__.py
torchfl/federated/agents/base.py
torchfl/federated/agents/v1.py
torchfl/federated/aggregators/__init__.py
torchfl/federated/aggregators/base.py
torchfl/federated/aggregators/fedavg.py
torchfl/federated/entrypoint.py
torchfl/federated/fl_params.py
torchfl/federated/samplers/__init__.py
torchfl/federated/samplers/base.py
torchfl/federated/samplers/random.py
torchfl/federated/types.py
torchfl/models/__init__.py
torchfl/models/core/__init__.py
torchfl/models/core/cifar/__init__.py
torchfl/models/core/cifar/cifar10/__init__.py
torchfl/models/core/cifar/cifar10/alexnet.py
torchfl/models/core/cifar/cifar10/densenet.py
torchfl/models/core/cifar/cifar10/lenet.py
torchfl/models/core/cifar/cifar10/mobilenet.py
torchfl/models/core/cifar/cifar10/resnet.py
torchfl/models/core/cifar/cifar10/shufflenetv2.py
torchfl/models/core/cifar/cifar10/squeezenet.py
torchfl/models/core/cifar/cifar10/vgg.py
torchfl/models/core/cifar/cifar100/__init__.py
torchfl/models/core/cifar/cifar100/alexnet.py
torchfl/models/core/cifar/cifar100/densenet.py
torchfl/models/core/cifar/cifar100/lenet.py
torchfl/models/core/cifar/cifar100/mobilenet.py
torchfl/models/core/cifar/cifar100/resnet.py
torchfl/models/core/cifar/cifar100/shufflenetv2.py
torchfl/models/core/cifar/cifar100/squeezenet.py
torchfl/models/core/cifar/cifar100/vgg.py
torchfl/models/core/emnist/__init__.py
torchfl/models/core/emnist/balanced/__init__.py
torchfl/models/core/emnist/balanced/alexnet.py
torchfl/models/core/emnist/balanced/densenet.py
torchfl/models/core/emnist/balanced/lenet.py
torchfl/models/core/emnist/balanced/mlp.py
torchfl/models/core/emnist/balanced/mobilenet.py
torchfl/models/core/emnist/balanced/resnet.py
torchfl-0.1.9.dist-info/LICENSE
torchfl-0.1.9.dist-info/WHEEL
torchfl-0.1.9.dist-info/METADATA
torchfl-0.1.9.dist-info/RECORD
