Metadata-Version: 2.1
Name: torchfl
Version: 0.1.9
Summary: A Python library for rapid prototyping, experimenting, and logging of federated learning using state-of-the-art models and datasets. Built using PyTorch and PyTorch Lightning.
Home-page: https://torchfl.readthedocs.io/en/latest/
License: GNU General Public License v3
Keywords: federated-learning,pytorch,pytorch-lightning,torchfl
Author: vivekkhimani
Author-email: vivekkhimani07@gmail.com
Requires-Python: >=3.10,<4.0
Classifier: Development Status :: 4 - Beta
Classifier: Intended Audience :: Developers
Classifier: License :: OSI Approved :: GNU General Public License v3 (GPLv3)
Classifier: License :: Other/Proprietary License
Classifier: Natural Language :: English
Classifier: Programming Language :: Python :: 3
Classifier: Programming Language :: Python :: 3.10
Classifier: Programming Language :: Python :: 3.11
Classifier: Programming Language :: Python :: 3.10
Requires-Dist: numpy (>=1.24.2,<2.0.0)
Requires-Dist: pytest (>=7.2.1,<8.0.0)
Requires-Dist: pytorch-lightning (>=1.9,<1.10)
Requires-Dist: rich (>=13.3.1,<14.0.0)
Requires-Dist: torch (>=1.13,<1.14)
Requires-Dist: torchvision (>=0.14,<0.15)
Project-URL: Documentation, https://torchfl.readthedocs.io/en/latest/
Project-URL: Repository, https://github.com/vivekkhimani/torchfl
